{
  "cars": [
    {
      "id": 1,
      "year": 1968,
      "brand": "Abarth",
      "model": "595 esseesse",
      "topspeed": 130,
      "power": 23.5,
      "acceleration": 24.7,
      "weight": 570,
      "cylinder": 2,
      "torgue": 44,
      "img": "1968_Abarth_595_esseesse.jpg"
    },
    {
      "id": 2,
      "year": 2010,
      "brand": "Abarth",
      "model": "500 esseesse",
      "topspeed": 211,
      "power": 118,
      "acceleration": 7.4,
      "weight": 1110,
      "cylinder": 4,
      "torgue": 230,
      "img": "2010_Abarth_500_esseesse.jpg"
    },
    {
      "id": 3,
      "year": 2007,
      "brand": "Alfa Romeo",
      "model": "8C Competizione",
      "topspeed": 292,
      "power": 332,
      "acceleration": 4.2,
      "weight": 1585,
      "cylinder": 8,
      "torgue": 470,
      "img": "2007_Alfa_Romeo_8C_Competizione.jpg"
    },
    {
      "id": 4,
      "year": 2011,
      "brand": "Alfa Romeo",
      "model": "TZ3 Stradale Zagato",
      "topspeed": 325,
      "power": 471,
      "acceleration": 3.6,
      "weight": 1497,
      "cylinder": 10,
      "torgue": 820,
      "img": "2011_Alfa_Romeo_TZ3_Stradale_zagato.jpg"
    },
    {
      "id": 5,
      "year": 2012,
      "brand": "Alfa Romeo",
      "model": "8C Spider",
      "topspeed": 295,
      "power": 332,
      "acceleration": 4.4,
      "weight": 1675,
      "cylinder": 8,
      "torgue": 470,
      "img": "2012_Alfa_Romeo_8C_Spider.jpg"
    },
    {
      "id": 6,
      "year": 1971,
      "brand": "AMC",
      "model": "Javelin AMX",
      "topspeed": 180,
      "power": 246,
      "acceleration": 7.6,
      "weight": 1563,
      "cylinder": 8,
      "torgue": 583,
      "img": "1971_AMC_Javelin_AMX.jpg"
    },
    {
      "id": 7,
      "year": 2012,
      "brand": "Ascari",
      "model": "KZ1R",
      "topspeed": 320,
      "power": 373,
      "acceleration": 3.7,
      "weight": 1330,
      "cylinder": 8,
      "torgue": 500,
      "img": "2012_Ascari_KZ1R.jpg"
    },
    {
      "id": 8,
      "year": 1958,
      "brand": "Aston Martin",
      "model": "DBR1",
      "topspeed": 290,
      "power": 190,
      "acceleration": 6.5,
      "weight": 875,
      "cylinder": 6,
      "torgue": 334,
      "img": "1958_Aston_Martin_DBR1.jpg"
    },
    {
      "id": 9,
      "year": 1964,
      "brand": "Aston Martin",
      "model": "DB5",
      "topspeed": 229,
      "power": 242,
      "acceleration": 7.1,
      "weight": 1465,
      "cylinder": 6,
      "torgue": 390,
      "img": "1964_Aston_Martin_DB5.jpg"
    },
    {
      "id": 10,
      "year": 2008,
      "brand": "Aston Martin",
      "model": "DBS",
      "topspeed": 305,
      "power": 380,
      "acceleration": 4.3,
      "weight": 1695,
      "cylinder": 12,
      "torgue": 569,
      "img": "2008_Aston_Martin_DBS.jpg"
    },
    {
      "id": 11,
      "year": 2010,
      "brand": "Aston Martin",
      "model": "One-77",
      "topspeed": 355,
      "power": 559,
      "acceleration": 3.5,
      "weight": 1500,
      "cylinder": 12,
      "torgue": 750,
      "img": "2010_Aston_Martin_One-77.jpg"
    },
    {
      "id": 12,
      "year": 2011,
      "brand": "Aston Martin",
      "model": "V12 Zagato",
      "topspeed": 305,
      "power": 381,
      "acceleration": 4.2,
      "weight": 1680,
      "cylinder": 12,
      "torgue": 570,
      "img": "2011_Aston_Martin_V12_Zagato.jpg"
    },
    {
      "id": 13,
      "year": 2012,
      "brand": "Aston Martin",
      "model": "Vanquish",
      "topspeed": 295,
      "power": 421,
      "acceleration": 4.1,
      "weight": 1739,
      "cylinder": 12,
      "torgue": 620,
      "img": "2012_Aston_Martin_Vanquish.jpg"
    },
    {
      "id": 14,
      "year": 2012,
      "brand": "Aston Martin",
      "model": "Virage",
      "topspeed": 299,
      "power": 365,
      "acceleration": 4.6,
      "weight": 1785,
      "cylinder": 12,
      "torgue": 570,
      "img": "2012_Aston_Martin_Virage.jpg"
    },
    {
      "id": 15,
      "year": 1983,
      "brand": "Audi",
      "model": "Sport Quattro",
      "topspeed": 248,
      "power": 225,
      "acceleration": 4.5,
      "weight": 1300,
      "cylinder": 5,
      "torgue": 350,
      "img": "1983_Audi_Sport_Quattro.jpg"
    },
    {
      "id": 16,
      "year": 2006,
      "brand": "Audi",
      "model": "RS4",
      "topspeed": 280,
      "power": 309,
      "acceleration": 4.8,
      "weight": 1650,
      "cylinder": 8,
      "torgue": 430,
      "img": "2006_Audi_RS4.jpg"
    },
    {
      "id": 17,
      "year": 2010,
      "brand": "Audi",
      "model": "TT RS Coupe",
      "topspeed": 280,
      "power": 250,
      "acceleration": 4.3,
      "weight": 1525,
      "cylinder": 5,
      "torgue": 450,
      "img": "2010_Audi_TT_RS_Coupe.jpg"
    },
    {
      "id": 18,
      "year": 2011,
      "brand": "Audi",
      "model": "R8 GT",
      "topspeed": 320,
      "power": 412,
      "acceleration": 3.6,
      "weight": 1600,
      "cylinder": 10,
      "torgue": 540,
      "img": "2011_Audi_R8_GT.jpg"
    },
    {
      "id": 19,
      "year": 2012,
      "brand": "Audi",
      "model": "R8 GT Spyder",
      "topspeed": 317,
      "power": 412,
      "acceleration": 3.8,
      "weight": 1640,
      "cylinder": 10,
      "torgue": 540,
      "img": "2012_Audi_R8_GT_Spyder.jpg"
    },
    {
      "id": 20,
      "year": 2013,
      "brand": "Audi",
      "model": "RS4 Avant",
      "topspeed": 280,
      "power": 331,
      "acceleration": 4.7,
      "weight": 1870,
      "cylinder": 8,
      "torgue": 430,
      "img": "2013_Audi_RS4_Avant.jpg"
    },
    {
      "id": 21,
      "year": 2012,
      "brand": "Bentley",
      "model": "Continental GT",
      "topspeed": 318,
      "power": 423,
      "acceleration": 4.5,
      "weight": 2320,
      "cylinder": 12,
      "torgue": 700,
      "img": "2012_Bentley_Continental_GT.jpg"
    },
    {
      "id": 22,
      "year": 1973,
      "brand": "BMW",
      "model": "2002 Turbo",
      "topspeed": 212,
      "power": 125,
      "acceleration": 7.1,
      "weight": 1080,
      "cylinder": 4,
      "torgue": 245,
      "img": "1973_BMW_2002_Turbo.jpg"
    },
    {
      "id": 23,
      "year": 1981,
      "brand": "BMW",
      "model": "M1",
      "topspeed": 265,
      "power": 207,
      "acceleration": 6,
      "weight": 1300,
      "cylinder": 6,
      "torgue": 329,
      "img": "1981_BMW_M1.jpg"
    },
    {
      "id": 24,
      "year": 1991,
      "brand": "BMW",
      "model": "M3",
      "topspeed": 241,
      "power": 160,
      "acceleration": 6.7,
      "weight": 1253,
      "cylinder": 4,
      "torgue": 244,
      "img": "1991_BMW_M3.jpg"
    },
    {
      "id": 25,
      "year": 2002,
      "brand": "BMW",
      "model": "M3-GTR",
      "topspeed": 250,
      "power": 283,
      "acceleration": 4.8,
      "weight": 1350,
      "cylinder": 8,
      "torgue": 390,
      "img": "2002_BMW_M3-GTR.jpg"
    },
    {
      "id": 26,
      "year": 2008,
      "brand": "BMW",
      "model": "M3",
      "topspeed": 280,
      "power": 309,
      "acceleration": 4.6,
      "weight": 1655,
      "cylinder": 8,
      "torgue": 400,
      "img": "2008_BMW_M3.jpg"
    },
    {
      "id": 27,
      "year": 2010,
      "brand": "BMW",
      "model": "M3 GTS",
      "topspeed": 305,
      "power": 331,
      "acceleration": 4.4,
      "weight": 1570,
      "cylinder": 8,
      "torgue": 441,
      "img": "2010_BMW_M3_GTS.jpg"
    },
    {
      "id": 28,
      "year": 2011,
      "brand": "BMW",
      "model": "BMW 1 Series M Coupe",
      "topspeed": 250,
      "power": 250,
      "acceleration": 4.5,
      "weight": 1495,
      "cylinder": 6,
      "torgue": 450,
      "img": "2011_BMW_1_Series_M_Coupe.jpg"
    },
    {
      "id": 29,
      "year": 2012,
      "brand": "BMW",
      "model": "M5",
      "topspeed": 306,
      "power": 412,
      "acceleration": 3.9,
      "weight": 1870,
      "cylinder": 8,
      "torgue": 679,
      "img": "2012_BMW_M5.jpg"
    },
    {
      "id": 30,
      "year": 2012,
      "brand": "BMW",
      "model": "Z4 sDrive28i",
      "topspeed": 250,
      "power": 183,
      "acceleration": 5.7,
      "weight": 1490,
      "cylinder": 4,
      "torgue": 350,
      "img": "2012_BMW_Z4_sDrive28i.jpg"
    },
    {
      "id": 31,
      "year": 2013,
      "brand": "BMW",
      "model": "M6 Coupe",
      "topspeed": 305,
      "power": 418,
      "acceleration": 3.9,
      "weight": 1930,
      "cylinder": 8,
      "torgue": 678,
      "img": "2013_BMW_M6_Coupe.jpg"
    },
    {
      "id": 32,
      "year": 2013,
      "brand": "BMW",
      "model": "M135i",
      "topspeed": 250,
      "power": 235,
      "acceleration": 4.7,
      "weight": 1513,
      "cylinder": 6,
      "torgue": 447,
      "img": "2013_BMW_M135i.jpg"
    },
    {
      "id": 33,
      "year": 2012,
      "brand": "Bowler",
      "model": "EXR s",
      "topspeed": 250,
      "power": 410,
      "acceleration": 4.4,
      "weight": 1750,
      "cylinder": 8,
      "torgue": 652,
      "img": "2012_Bowler_EXR_S.jpg"
    },
    {
      "id": 34,
      "year": 1992,
      "brand": "Bugatti",
      "model": "EB110 Super Sport",
      "topspeed": 342,
      "power": 456,
      "acceleration": 3.5,
      "weight": 1418,
      "cylinder": 12,
      "torgue": 651,
      "img": "1992_Bugatti_EB110_Super_Sport.jpg"
    },
    {
      "id": 35,
      "year": 2011,
      "brand": "Bugatti",
      "model": "Veyron Super Sport",
      "topspeed": 434,
      "power": 882,
      "acceleration": 2.8,
      "weight": 1834,
      "cylinder": 16,
      "torgue": 1499,
      "img": "2011_Bugatti_Veyron_Super_Sport.jpg"
    },
    {
      "id": 36,
      "year": 2011,
      "brand": "Cadillac",
      "model": "CTS-V Coupe",
      "topspeed": 308,
      "power": 415,
      "acceleration": 4.0,
      "weight": 1783,
      "cylinder": 8,
      "torgue": 747,
      "img": "2011_Cadillac_CTS-V_Coupe.jpg"
    },
    {
      "id": 37,
      "year": 2012,
      "brand": "Cadillac",
      "model": "Escalade ESV",
      "topspeed": 170,
      "power": 301,
      "acceleration": 6.7,
      "weight": 2713,
      "cylinder": 8,
      "torgue": 564,
      "img": "2012_Cadillac_Escalade_ESV.jpg"
    },
    {
      "id": 38,
      "year": 1957,
      "brand": "Chevrolet",
      "model": "Bel Air",
      "topspeed": 180,
      "power": 164,
      "acceleration": 8.6,
      "weight": 1514,
      "cylinder": 8,
      "torgue": 407,
      "img": "1957_Chevrolet_Bel_Air.jpg"
    },
    {
      "id": 39,
      "year": 1964,
      "brand": "Chevrolet",
      "model": "Impala SS 409",
      "topspeed": 204,
      "power": 317,
      "acceleration": 6.9,
      "weight": 1759,
      "cylinder": 8,
      "torgue": 576,
      "img": "1964_Chevrolet_Impala_SS_409.jpg"
    },
    {
      "id": 40,
      "year": 1967,
      "brand": "Chevrolet",
      "model": "Corvette Stingray 427",
      "topspeed": 276,
      "power": 324,
      "acceleration": 4.8,
      "weight": 1535,
      "cylinder": 8,
      "torgue": 624,
      "img": "1967_Chevrolet_Corvette_Stingray_427.jpg"
    },
    {
      "id": 41,
      "year": 1969,
      "brand": "Chevrolet",
      "model": "Camaro SS Coupe",
      "topspeed": 230,
      "power": 280,
      "acceleration": 6.5,
      "weight": 1600,
      "cylinder": 8,
      "torgue": 563,
      "img": "1969_Chevrolet_Camaro_SS_Coupe.jpg"
    },
    {
      "id": 42,
      "year": 2009,
      "brand": "Chevrolet",
      "model": "Corvette ZR1",
      "topspeed": 330,
      "power": 476,
      "acceleration": 3.2,
      "weight": 1520,
      "cylinder": 8,
      "torgue": 819,
      "img": "2009_Chevrolet_Corvette_ZR1.jpg"
    },
    {
      "id": 43,
      "year": 2010,
      "brand": "Chevrolet",
      "model": "Corvette GrandSport Convertible",
      "topspeed": 306,
      "power": 325,
      "acceleration": 4.3,
      "weight": 1534,
      "cylinder": 8,
      "torgue": 580,
      "img": "2010_Chevrolet_GrandSport_Convertible.jpg"
    },
    {
      "id": 44,
      "year": 2012,
      "brand": "Chevrolet",
      "model": "Camaro ZL1",
      "topspeed": 296,
      "power": 433,
      "acceleration": 4.6,
      "weight": 1838,
      "cylinder": 8,
      "torgue": 755,
      "img": "2012_Chevrolet_Camaro_ZL1.jpg"
    },
    {
      "id": 45,
      "year": 2010,
      "brand": "Citroen",
      "model": "DS3 Racing",
      "topspeed": 235,
      "power": 152,
      "acceleration": 6.5,
      "weight": 1165,
      "cylinder": 4,
      "torgue": 275,
      "img": "2010_Citroen_DS3_Racing.jpg"
    },
    {
      "id": 46,
      "year": 2010,
      "brand": "Devon",
      "model": "GTX",
      "topspeed": 322,
      "power": 485,
      "acceleration": 3.4,
      "weight": 1451,
      "cylinder": 10,
      "torgue": 796,
      "img": "2010_Devon_GTX.jpg"
    },
    {
      "id": 47,
      "year": 1969,
      "brand": "Dodge",
      "model": "Charger RT",
      "topspeed": 220,
      "power": 317,
      "acceleration": 5.3,
      "weight": 1665,
      "cylinder": 8,
      "torgue": 664,
      "img": "1969_Dodge_Charger_RT.jpg"
    },
    {
      "id": 48,
      "year": 2012,
      "brand": "Dodge",
      "model": "Challenger SRT8 392",
      "topspeed": 270,
      "power": 350,
      "acceleration": 5.0,
      "weight": 1887,
      "cylinder": 8,
      "torgue": 637,
      "img": "2012_Dodge_Challenger_SRT8_392.jpg"
    },
    {
      "id": 49,
      "year": 2012,
      "brand": "Dodge",
      "model": "Charger SRT8",
      "topspeed": 286,
      "power": 350,
      "acceleration": 4.9,
      "weight": 1980,
      "cylinder": 8,
      "torgue": 637,
      "img": "2012_Dodge_Charger_SRT8.jpg"
    },
    {
      "id": 50,
      "year": 2012,
      "brand": "Eagle",
      "model": "Speedster",
      "topspeed": 260,
      "power": 246,
      "acceleration": 5.2,
      "weight": 1008,
      "cylinder": 6,
      "torgue": 489,
      "img": "2012_Eagle_Speedster.jpg"
    },
    {
      "id": 51,
      "year": 1957,
      "brand": "Ferrari",
      "model": "250 California",
      "topspeed": 273,
      "power": 195,
      "acceleration": 8.0,
      "weight": 1050,
      "cylinder": 12,
      "torgue": 255,
      "img": "1957_Ferrari_250_California.jpg"
    },
    {
      "id": 52,
      "year": 1957,
      "brand": "Ferrari",
      "model": "250 Testa Rossa",
      "topspeed": 270,
      "power": 224,
      "acceleration": 6.2,
      "weight": 920,
      "cylinder": 12,
      "torgue": 302,
      "img": "1957_Ferrari_250_Testa_Rossa.jpg"
    },
    {
      "id": 53,
      "year": 1962,
      "brand": "Ferrari",
      "model": "250_GTO",
      "topspeed": 280,
      "power": 224,
      "acceleration": 6.0,
      "weight": 1043,
      "cylinder": 12,
      "torgue": 293,
      "img": "1962_Ferrari_250_GTO.jpg"
    },
    {
      "id": 54,
      "year": 1984,
      "brand": "Ferrari",
      "model": "GTO",
      "topspeed": 306,
      "power": 295,
      "acceleration": 4.7,
      "weight": 1160,
      "cylinder": 8,
      "torgue": 496,
      "img": "1984_Ferrari_GTO.jpg"
    },
    {
      "id": 55,
      "year": 1987,
      "brand": "Ferrari",
      "model": "F40",
      "topspeed": 327,
      "power": 356,
      "acceleration": 4.3,
      "weight": 1352,
      "cylinder": 8,
      "torgue": 575,
      "img": "1987_Ferrari_F40.jpg"
    },
    {
      "id": 56,
      "year": 1989,
      "brand": "Ferrari",
      "model": "F40 Competizione",
      "topspeed": 367,
      "power": 515,
      "acceleration": 3.2,
      "weight": 1050,
      "cylinder": 8,
      "torgue": 713,
      "img": "1989_Ferrari_F40_Competizione.jpg"
    },
    {
      "id": 57,
      "year": 1991,
      "brand": "Ferrari",
      "model": "512 TR",
      "topspeed": 316,
      "power": 314,
      "acceleration": 4.5,
      "weight": 1674,
      "cylinder": 12,
      "torgue": 488,
      "img": "1991_Ferrari_512_TR.jpg"
    },
    {
      "id": 58,
      "year": 1995,
      "brand": "Ferrari",
      "model": "F50",
      "topspeed": 326,
      "power": 383,
      "acceleration": 3.8,
      "weight": 1350,
      "cylinder": 12,
      "torgue": 470,
      "img": "1995_Ferrari_F50.jpg"
    },
    {
      "id": 59,
      "year": 1995,
      "brand": "Ferrari",
      "model": "F355 Challenge",
      "topspeed": 300,
      "power": 283,
      "acceleration": 4.8,
      "weight": 1354,
      "cylinder": 8,
      "torgue": 363,
      "img": "1995_Ferrari_F355_Challenge.jpg"
    },
    {
      "id": 60,
      "year": 1996,
      "brand": "Ferrari",
      "model": "F50 GT",
      "topspeed": 376,
      "power": 559,
      "acceleration": 2.9,
      "weight": 908,
      "cylinder": 12,
      "torgue": 520,
      "img": "1996_Ferrari_F50_GT.jpg"
    },
    {
      "id": 61,
      "year": 2002,
      "brand": "Ferrari",
      "model": "Enzo Ferrari",
      "topspeed": 355,
      "power": 485,
      "acceleration": 3.6,
      "weight": 1400,
      "cylinder": 12,
      "torgue": 658,
      "img": "2002_Ferrari_Enzo_Ferrari.jpg"
    },
    {
      "id": 62,
      "year": 2003,
      "brand": "Ferrari",
      "model": "Challenge Stradale",
      "topspeed": 283,
      "power": 305,
      "acceleration": 4.1,
      "weight": 1290,
      "cylinder": 8,
      "torgue": 373,
      "img": "2003_Ferrari_Challenge_Stradale.jpg"
    },
    {
      "id": 63,
      "year": 2005,
      "brand": "Ferrari",
      "model": "FXX",
      "topspeed": 345,
      "power": 588,
      "acceleration": 2.9,
      "weight": 1239,
      "cylinder": 12,
      "torgue": 686,
      "img": "2005_Ferrari_FXX.jpg"
    },
    {
      "id": 64,
      "year": 2007,
      "brand": "Ferrari",
      "model": "430 Scuderia",
      "topspeed": 320,
      "power": 375,
      "acceleration": 3.3,
      "weight": 1349,
      "cylinder": 8,
      "torgue": 469,
      "img": "2007_Ferrari_430_Scuderia.jpg"
    },
    {
      "id": 65,
      "year": 2009,
      "brand": "Ferrari",
      "model": "California",
      "topspeed": 310,
      "power": 338,
      "acceleration": 3.9,
      "weight": 1735,
      "cylinder": 8,
      "torgue": 485,
      "img": "2009_Ferrari_California.jpg"
    },
    {
      "id": 66,
      "year": 2010,
      "brand": "Ferrari",
      "model": "458 Italia",
      "topspeed": 338,
      "power": 419,
      "acceleration": 3.3,
      "weight": 1485,
      "cylinder": 8,
      "torgue": 540,
      "img": "2010_Ferrari_458_Italia.jpg"
    },
    {
      "id": 67,
      "year": 2010,
      "brand": "Ferrari",
      "model": "599XX",
      "topspeed": 339,
      "power": 515,
      "acceleration": 3.1,
      "weight": 1520,
      "cylinder": 12,
      "torgue": 650,
      "img": "2010_Ferrari_599XX.jpg"
    },
    {
      "id": 68,
      "year": 2011,
      "brand": "Ferrari",
      "model": "458 Spider",
      "topspeed": 325,
      "power": 419,
      "acceleration": 3.3,
      "weight": 1535,
      "cylinder": 8,
      "torgue": 540,
      "img": "2011_Ferrari_458_Spider.jpg"
    },
    {
      "id": 69,
      "year": 2011,
      "brand": "Ferrari",
      "model": "FF",
      "topspeed": 340,
      "power": 485,
      "acceleration": 3.5,
      "weight": 1880,
      "cylinder": 12,
      "torgue": 683,
      "img": "2011_Ferrari_FF.jpg"
    },
    {
      "id": 70,
      "year": 2012,
      "brand": "Ferrari",
      "model": "599XX Evoluzione",
      "topspeed": 315,
      "power": 552,
      "acceleration": 3.0,
      "weight": 1365,
      "cylinder": 12,
      "torgue": 700,
      "img": "2012_Ferrari_599XX_Evoluzione.jpg"
    },
    {
      "id": 71,
      "year": 2012,
      "brand": "Ferrari",
      "model": "F12berlinetta",
      "topspeed": 345,
      "power": 544,
      "acceleration": 3.0,
      "weight": 1630,
      "cylinder": 12,
      "torgue": 690,
      "img": "2012_Ferrari_F12berlinetta.jpg"
    },
    {
      "id": 72,
      "year": 1956,
      "brand": "Ford",
      "model": "F100",
      "topspeed": 113,
      "power": 129,
      "acceleration": 10.5,
      "weight": 1508,
      "cylinder": 8,
      "torgue": 353,
      "img": "1956_Ford_F100.jpg"
    },
    {
      "id": 73,
      "year": 1966,
      "brand": "Ford",
      "model": "Country Squire",
      "topspeed": 237,
      "power": 235,
      "acceleration": 6.2,
      "weight": 1837,
      "cylinder": 8,
      "torgue": 579,
      "img": "1966_Ford_Country_Squire.jpg"
    },
    {
      "id": 74,
      "year": 1966,
      "brand": "Ford",
      "model": "GT40 MkII",
      "topspeed": 320,
      "power": 362,
      "acceleration": 5.5,
      "weight": 1217,
      "cylinder": 8,
      "torgue": 644,
      "img": "1966_Ford_GT40_MkII.jpg"
    },
    {
      "id": 75,
      "year": 1970,
      "brand": "Ford",
      "model": "Mustang Boss 429",
      "topspeed": 206,
      "power": 280,
      "acceleration": 6.8,
      "weight": 1685,
      "cylinder": 8,
      "torgue": 610,
      "img": "1970_Ford_Mustang_Boss_429.jpg"
    },
    {
      "id": 76,
      "year": 1987,
      "brand": "Ford",
      "model": "Sierra Cosworth RS500",
      "topspeed": 242,
      "power": 167,
      "acceleration": 6.0,
      "weight": 1240,
      "cylinder": 4,
      "torgue": 279,
      "img": "1987_Ford_Sierra_Cosworth_RS500.jpg"
    },
    {
      "id": 77,
      "year": 1992,
      "brand": "Ford",
      "model": "Escort RS Cosworth",
      "topspeed": 242,
      "power": 167,
      "acceleration": 6.7,
      "weight": 1275,
      "cylinder": 4,
      "torgue": 304,
      "img": "1992_Ford_Escort_RS_Cosworth.jpg"
    },
    {
      "id": 78,
      "year": 1995,
      "brand": "Ford",
      "model": "Mustang Cobra R",
      "topspeed": 247,
      "power": 224,
      "acceleration": 5.4,
      "weight": 1463,
      "cylinder": 8,
      "torgue": 495,
      "img": "1995_Ford_Mustang_Cobra_R.jpg"
    },
    {
      "id": 79,
      "year": 2005,
      "brand": "Ford",
      "model": "GT",
      "topspeed": 330,
      "power": 410,
      "acceleration": 3.9,
      "weight": 1538,
      "cylinder": 8,
      "torgue": 678,
      "img": "2005_Ford_GT.jpg"
    },
    {
      "id": 80,
      "year": 2006,
      "brand": "Ford",
      "model": "GTX1",
      "topspeed": 330,
      "power": 410,
      "acceleration": 4.1,
      "weight": 1588,
      "cylinder": 8,
      "torgue": 678,
      "img": "2006_Ford_GTX1.jpg"
    },
    {
      "id": 81,
      "year": 2010,
      "brand": "Ford",
      "model": "Focus RS500",
      "topspeed": 266,
      "power": 257,
      "acceleration": 5.5,
      "weight": 1468,
      "cylinder": 5,
      "torgue": 460,
      "img": "2010_Ford_Focus_RS500.jpg"
    },
    {
      "id": 82,
      "year": 2011,
      "brand": "Ford",
      "model": "F-150 SVT Raptor",
      "topspeed": 273,
      "power": 306,
      "acceleration": 7.1,
      "weight": 2724,
      "cylinder": 8,
      "torgue": 588,
      "img": "2011_Ford_F-150_SVT_Raptor.jpg"
    },
    {
      "id": 83,
      "year": 2011,
      "brand": "Ford",
      "model": "Transit SuperSportVan",
      "topspeed": 197,
      "power": 148,
      "acceleration": 13.5,
      "weight": 2038,
      "cylinder": 5,
      "torgue": 469,
      "img": "2011_Ford_Transit_SuperSportVan.jpg"
    },
    {
      "id": 84,
      "year": 2012,
      "brand": "Ford",
      "model": "Mustang Boss 302",
      "topspeed": 253,
      "power": 216,
      "acceleration": 4.2,
      "weight": 1474,
      "cylinder": 8,
      "torgue": 393,
      "img": "2012_Ford_Mustang_Boss_302.jpg"
    },
    {
      "id": 85,
      "year": 2013,
      "brand": "Ford",
      "model": "Focus ST",
      "topspeed": 248,
      "power": 184,
      "acceleration": 6.4,
      "weight": 1350,
      "cylinder": 4,
      "torgue": 360,
      "img": "2013_Ford_Focus_ST.jpg"
    },
    {
      "id": 86,
      "year": 2013,
      "brand": "Ford",
      "model": "Shelby GT500",
      "topspeed": 330,
      "power": 494,
      "acceleration": 3.7,
      "weight": 1768,
      "cylinder": 8,
      "torgue": 856,
      "img": "2013_Ford_Shelby_GT500.jpg"
    },
    {
      "id": 87,
      "year": 1983,
      "brand": "GMC",
      "model": "Vandura G-1500",
      "topspeed": 165,
      "power": 123,
      "acceleration": 16.0,
      "weight": 2290,
      "cylinder": 8,
      "torgue": 373,
      "img": "1983_GMC_Vandura_G-1500.jpg"
    },
    {
      "id": 88,
      "year": 2009,
      "brand": "Gumpert",
      "model": "Apollo S",
      "topspeed": 330,
      "power": 515,
      "acceleration": 3.1,
      "weight": 1350,
      "cylinder": 8,
      "torgue": 875,
      "img": "2009_Gumpert_Apollo_S.jpg"
    },
    {
      "id": 89,
      "year": 2012,
      "brand": "Gumpert",
      "model": "Apollo Enraged",
      "topspeed": 330,
      "power": 573,
      "acceleration": 2.9,
      "weight": 1325,
      "cylinder": 8,
      "torgue": 919,
      "img": "2012_Gumpert_Apollo_Enraged.jpg"
    },
    {
      "id": 90,
      "year": 2012,
      "brand": "Hennessey",
      "model": "Venom GT",
      "topspeed": 418,
      "power": 895,
      "acceleration": 2.9,
      "weight": 1218,
      "cylinder": 8,
      "torgue": 1566,
      "img": "2012_Hennessey_Venom_GT.jpg"
    },
    {
      "id": 91,
      "year": 1986,
      "brand": "Honda",
      "model": "Civic Si",
      "topspeed": 178,
      "power": 68,
      "acceleration": 10.8,
      "weight": 887,
      "cylinder": 4,
      "torgue": 126,
      "img": "1986_Honda_Civic_Si.jpg"
    },
    {
      "id": 92,
      "year": 2002,
      "brand": "Honda",
      "model": "Integra Type-R",
      "topspeed": 225,
      "power": 162,
      "acceleration": 7.3,
      "weight": 1190,
      "cylinder": 4,
      "torgue": 206,
      "img": "2002_Honda_Integra_Type-R.jpg"
    },
    {
      "id": 93,
      "year": 2003,
      "brand": "Honda",
      "model": "S2000",
      "topspeed": 240,
      "power": 184,
      "acceleration": 6.2,
      "weight": 1250,
      "cylinder": 4,
      "torgue": 218,
      "img": "2003_Honda_S2000.jpg"
    },
    {
      "id": 94,
      "year": 2004,
      "brand": "Honda",
      "model": "Civic Type-R",
      "topspeed": 235,
      "power": 158,
      "acceleration": 6.8,
      "weight": 1190,
      "cylinder": 4,
      "torgue": 202,
      "img": "2004_Honda_Civic_Type-R.jpg"
    },
    {
      "id": 95,
      "year": 2005,
      "brand": "Honda",
      "model": "NSX-R GT",
      "topspeed": 280,
      "power": 216,
      "acceleration": 4.4,
      "weight": 1270,
      "cylinder": 6,
      "torgue": 305,
      "img": "2005_Honda_NSX-R_GT.jpg"
    },
    {
      "id": 96,
      "year": 2012,
      "brand": "Honda",
      "model": "HPD Fit",
      "topspeed": 211,
      "power": 87,
      "acceleration": 8.2,
      "weight": 1129,
      "cylinder": 4,
      "torgue": 144,
      "img": "2012_Honda_HPD_Fit.jpg"
    },
    {
      "id": 97,
      "year": 2013,
      "brand": "Honda",
      "model": "Civic Si Coupe",
      "topspeed": 237,
      "power": 150,
      "acceleration": 7.3,
      "weight": 1305,
      "cylinder": 4,
      "torgue": 230,
      "img": "2013_Honda_Civic_Si_Coupe.jpg"
    },
    {
      "id": 98,
      "year": 2006,
      "brand": "Hummer",
      "model": "H1 Alpha Open Top",
      "topspeed": 113,
      "power": 224,
      "acceleration": 18.5,
      "weight": 3428,
      "cylinder": 8,
      "torgue": 705,
      "img": "2006_Hummer_H1_Alpha_Open_Top.jpg"
    },
    {
      "id": 99,
      "year": 2013,
      "brand": "Hyundai",
      "model": "Genesis Coupe 3.8 Track",
      "topspeed": 260,
      "power": 260,
      "acceleration": 5.9,
      "weight": 1557,
      "cylinder": 6,
      "torgue": 400,
      "img": "2013_Hyundai_Genesis_Coupe.jpg"
    },
    {
      "id": 100,
      "year": 2012,
      "brand": "Infiniti",
      "model": "IPL G Coupe",
      "topspeed": 270,
      "power": 260,
      "acceleration": 5.6,
      "weight": 1691,
      "cylinder": 6,
      "torgue": 374,
      "img": "2012_Infiniti_IPL_G_Coupe.jpg"
    },
    {
      "id": 101,
      "year": 1956,
      "brand": "Jaguar",
      "model": "D-Type",
      "topspeed": 270,
      "power": 183,
      "acceleration": 5.0,
      "weight": 953,
      "cylinder": 6,
      "torgue": 328,
      "img": "1956_Jaguar_D-Type.jpg"
    },
    {
      "id": 102,
      "year": 1961,
      "brand": "Jaguar",
      "model": "E-Type S1",
      "topspeed": 256,
      "power": 198,
      "acceleration": 7.1,
      "weight": 1315,
      "cylinder": 6,
      "torgue": 353,
      "img": "1961_Jaguar_E-Type_S1.jpg"
    },
    {
      "id": 103,
      "year": 2012,
      "brand": "Jaguar",
      "model": "XKR-S",
      "topspeed": 300,
      "power": 404,
      "acceleration": 4.2,
      "weight": 1753,
      "cylinder": 8,
      "torgue": 679,
      "img": "2012_Jaguar_XKR-S.jpg"
    },
    {
      "id": 104,
      "year": 2012,
      "brand": "Jeep",
      "model": "Grand Cherokee SRT8",
      "topspeed": 250,
      "power": 347,
      "acceleration": 5.0,
      "weight": 2388,
      "cylinder": 8,
      "torgue": 630,
      "img": "2012_Jeep_Grand_Cherokee_SRT8.jpg"
    },
    {
      "id": 105,
      "year": 2012,
      "brand": "Jeep",
      "model": "Wrangler Rubicon",
      "topspeed": 242,
      "power": 213,
      "acceleration": 6.5,
      "weight": 1874,
      "cylinder": 6,
      "torgue": 353,
      "img": "2012_Jeep_Wrangler_Rubicon.jpg"
    },
    {
      "id": 106,
      "year": 2010,
      "brand": "Joss",
      "model": "JT1",
      "topspeed": 300,
      "power": 373,
      "acceleration": 3.1,
      "weight": 940,
      "cylinder": 8,
      "torgue": 600,
      "img": "2010_Joss_JT1.jpg"
    },
    {
      "id": 107,
      "year": 2009,
      "brand": "Koenigsegg",
      "model": "CCX-R Edition",
      "topspeed": 403,
      "power": 759,
      "acceleration": 2.9,
      "weight": 1428,
      "cylinder": 8,
      "torgue": 1079,
      "img": "2009_Koenigsegg_CCX-R_Edition.jpg"
    },
    {
      "id": 108,
      "year": 2011,
      "brand": "Koenigsegg",
      "model": "Agera",
      "topspeed": 420,
      "power": 705,
      "acceleration": 3.0,
      "weight": 1435,
      "cylinder": 8,
      "torgue": 1100,
      "img": "2011_Koenigsegg_Agera.jpg"
    },
    {
      "id": 109,
      "year": 1967,
      "brand": "Lamborghini",
      "model": "Miura P400",
      "topspeed": 288,
      "power": 261,
      "acceleration": 5.5,
      "weight": 1245,
      "cylinder": 12,
      "torgue": 369,
      "img": "1967_Lamborghini_Miura_P400.jpg"
    },
    {
      "id": 110,
      "year": 1988,
      "brand": "Lamborghini",
      "model": "Countach LP5000 QV",
      "topspeed": 298,
      "power": 339,
      "acceleration": 4.8,
      "weight": 1490,
      "cylinder": 12,
      "torgue": 500,
      "img": "1988_Lamborghini_Countach_LP5000_QV.jpg"
    },
    {
      "id": 111,
      "year": 1997,
      "brand": "Lamborghini",
      "model": "Diablo SV",
      "topspeed": 333,
      "power": 395,
      "acceleration": 4.1,
      "weight": 1576,
      "cylinder": 12,
      "torgue": 605,
      "img": "1997_Lamborghini_Diablo_SV.jpg"
    },
    {
      "id": 112,
      "year": 2009,
      "brand": "Lamborghini",
      "model": "Reventon Roadster",
      "topspeed": 346,
      "power": 493,
      "acceleration": 3.4,
      "weight": 1690,
      "cylinder": 12,
      "torgue": 660,
      "img": "2009_Lamborghini_Reventon_Roadster.jpg"
    },
    {
      "id": 113,
      "year": 2010,
      "brand": "Lamborghini",
      "model": "Murcielago LP 670-4 SV",
      "topspeed": 342,
      "power": 485,
      "acceleration": 3.0,
      "weight": 1746,
      "cylinder": 12,
      "torgue": 660,
      "img": "2010_Lamborghini_Murcielago_LP_670-4_SV.jpg"
    },
    {
      "id": 114,
      "year": 2011,
      "brand": "Lamborghini",
      "model": "Gallardo LP 570-4 Superleggera",
      "topspeed": 326,
      "power": 419,
      "acceleration": 3.4,
      "weight": 1574,
      "cylinder": 10,
      "torgue": 540,
      "img": "2011_Lamborghini_Gallardo_LP_570-4_Superleggera.jpg"
    },
    {
      "id": 115,
      "year": 2011,
      "brand": "Lamborghini",
      "model": "Sesto Elemento",
      "topspeed": 322,
      "power": 426,
      "acceleration": 2.6,
      "weight": 999,
      "cylinder": 10,
      "torgue": 540,
      "img": "2011_Lamborghini_Sesto_Elemento.jpg"
    },
    {
      "id": 116,
      "year": 2012,
      "brand": "Lamborghini",
      "model": "Aventador J",
      "topspeed": 354,
      "power": 522,
      "acceleration": 2.9,
      "weight": 1642,
      "cylinder": 12,
      "torgue": 690,
      "img": "2012_Lamborghini_Aventador_J.jpg"
    },
    {
      "id": 117,
      "year": 2012,
      "brand": "Lamborghini",
      "model": "Aventador LP700-4",
      "topspeed": 354,
      "power": 522,
      "acceleration": 2.9,
      "weight": 1575,
      "cylinder": 12,
      "torgue": 690,
      "img": "2012_Lamborghini_Aventador_LP700-4.jpg"
    },
    {
      "id": 118,
      "year": 2012,
      "brand": "Lamborghini",
      "model": "Gallardo LP 570-4 Spyder Performante",
      "topspeed": 323,
      "power": 419,
      "acceleration": 3.9,
      "weight": 1485,
      "cylinder": 10,
      "torgue": 540,
      "img": "2012_Lamborghini_LP_570-4_Spyder_Performante.jpg"
    },
    {
      "id": 119,
      "year": 1974,
      "brand": "Lancia",
      "model": "Stratos HF Stradale",
      "topspeed": 232,
      "power": 142,
      "acceleration": 6.7,
      "weight": 980,
      "cylinder": 6,
      "torgue": 224,
      "img": "1974_Lancia_Stratos_HF_Stradale.jpg"
    },
    {
      "id": 120,
      "year": 1982,
      "brand": "Lancia",
      "model": "037 Stradale",
      "topspeed": 229,
      "power": 151,
      "acceleration": 6.7,
      "weight": 1152,
      "cylinder": 4,
      "torgue": 233,
      "img": "1982_Lancia_037_Stradale.jpg"
    },
    {
      "id": 121,
      "year": 1986,
      "brand": "Lancia",
      "model": "Delta S4 Stradale",
      "topspeed": 225,
      "power": 184,
      "acceleration": 5.8,
      "weight": 1200,
      "cylinder": 4,
      "torgue": 290,
      "img": "1986_Lancia_Delta_S4_Stradale.jpg"
    },
    {
      "id": 122,
      "year": 1992,
      "brand": "Lancia",
      "model": "Delta Integrale EVO",
      "topspeed": 220,
      "power": 157,
      "acceleration": 5.7,
      "weight": 1300,
      "cylinder": 4,
      "torgue": 304,
      "img": "1992_Lancia_Delta_Integrale_EVO.jpg"
    },
    {
      "id": 123,
      "year": 2012,
      "brand": "Land Rover",
      "model": "Range Rover Supercharged",
      "topspeed": 225,
      "power": 375,
      "acceleration": 5.3,
      "weight": 2810,
      "cylinder": 8,
      "torgue": 625,
      "img": "2012_Land_Rover_Range_Rover_Supercharged.jpg"
    },
    {
      "id": 124,
      "year": 2009,
      "brand": "Lexus",
      "model": "IS F",
      "topspeed": 270,
      "power": 310,
      "acceleration": 5.0,
      "weight": 1715,
      "cylinder": 8,
      "torgue": 503,
      "img": "2009_Lexus_IS_F.jpg"
    },
    {
      "id": 125,
      "year": 2010,
      "brand": "Lexus",
      "model": "LF-A",
      "topspeed": 325,
      "power": 412,
      "acceleration": 4.0,
      "weight": 1480,
      "cylinder": 10,
      "torgue": 480,
      "img": "2010_Lexus_LF-A.jpg"
    },
    {
      "id": 126,
      "year": 2012,
      "brand": "Lexus",
      "model": "LF-A Nürburgring Edition",
      "topspeed": 326,
      "power": 419,
      "acceleration": 3.7,
      "weight": 1444,
      "cylinder": 10,
      "torgue": 480,
      "img": "2012_Lexus_LF-A_Nurburgring_Edition.jpg"
    },
    {
      "id": 127,
      "year": 2006,
      "brand": "Lotus",
      "model": "Exige Cup 240",
      "topspeed": 249,
      "power": 181,
      "acceleration": 5.2,
      "weight": 930,
      "cylinder": 4,
      "torgue": 236,
      "img": "2006_Lotus_Exige_Cup_240.jpg"
    },
    {
      "id": 128,
      "year": 2009,
      "brand": "Lotus",
      "model": "2-Eleven",
      "topspeed": 249,
      "power": 188,
      "acceleration": 4.2,
      "weight": 745,
      "cylinder": 4,
      "torgue": 243,
      "img": "Lotus.jpg"
    },
    {
      "id": 129,
      "year": 2011,
      "brand": "Lotus",
      "model": "Evora S",
      "topspeed": 277,
      "power": 258,
      "acceleration": 4.6,
      "weight": 1437,
      "cylinder": 6,
      "torgue": 400,
      "img": "Lotus.jpg"
    },
    {
      "id": 130,
      "year": 2012,
      "brand": "Lotus",
      "model": "Exige S",
      "topspeed": 273,
      "power": 257,
      "acceleration": 4.1,
      "weight": 1176,
      "cylinder": 6,
      "torgue": 400,
      "img": "Lotus.jpg"
    },
    {
      "id": 131,
      "year": 2008,
      "brand": "Maserati",
      "model": "MC12 Versione Corse",
      "topspeed": 345,
      "power": 564,
      "acceleration": 3.8,
      "weight": 1200,
      "cylinder": 12,
      "torgue": 709,
      "img": "2008_Maserati_MC12_Versione_Corse.jpg"
    },
    {
      "id": 132,
      "year": 2010,
      "brand": "Maserati",
      "model": "GranTurismo S",
      "topspeed": 298,
      "power": 322,
      "acceleration": 4.5,
      "weight": 1881,
      "cylinder": 8,
      "torgue": 490,
      "img": "2010_Maserati_GranTurismo_S.jpg"
    },
    {
      "id": 133,
      "year": 1973,
      "brand": "Mazda",
      "model": "RX-3",
      "topspeed": 180,
      "power": 82,
      "acceleration": 10.0,
      "weight": 934,
      "cylinder": 2,
      "torgue": 136,
      "img": "1973_Mazda_RX-3.jpg"
    },
    {
      "id": 134,
      "year": 1994,
      "brand": "Mazda",
      "model": "MX-5 Miata",
      "topspeed": 197,
      "power": 95,
      "acceleration": 8.2,
      "weight": 1057,
      "cylinder": 4,
      "torgue": 149,
      "img": "1994_Mazda_MX-5_Miata.jpg"
    },
    {
      "id": 135,
      "year": 1997,
      "brand": "Mazda",
      "model": "RX-7",
      "topspeed": 259,
      "power": 195,
      "acceleration": 5.4,
      "weight": 1284,
      "cylinder": 2,
      "torgue": 294,
      "img": "1997_Mazda_RX-7.jpg"
    },
    {
      "id": 136,
      "year": 2004,
      "brand": "Mazda",
      "model": "RX-8 Mazdaspeed",
      "topspeed": 240,
      "power": 186,
      "acceleration": 6.0,
      "weight": 1406,
      "cylinder": 2,
      "torgue": 224,
      "img": "2004_Mazda_RX-8_Mazdaspeed.jpg"
    },
    {
      "id": 137,
      "year": 1993,
      "brand": "McLaren",
      "model": "F1",
      "topspeed": 386,
      "power": 468,
      "acceleration": 3.5,
      "weight": 1288,
      "cylinder": 12,
      "torgue": 651,
      "img": "1993_McLaren_F1.jpg"
    },
    {
      "id": 138,
      "year": 1997,
      "brand": "McLaren",
      "model": "F1 GT",
      "topspeed": 331,
      "power": 461,
      "acceleration": 3.1,
      "weight": 1120,
      "cylinder": 12,
      "torgue": 651,
      "img": "1997_McLaren_F1_GT.jpg"
    },
    {
      "id": 139,
      "year": 2011,
      "brand": "McLaren",
      "model": "MP4-12C",
      "topspeed": 333,
      "power": 441,
      "acceleration": 3.2,
      "weight": 1375,
      "cylinder": 8,
      "torgue": 600,
      "img": "2011_McLaren_MP4-12C.jpg"
    },
    {
      "id": 140,
      "year": 1954,
      "brand": "Mercedes-Benz",
      "model": "300SL Gullwing Coupe",
      "topspeed": 261,
      "power": 180,
      "acceleration": 7.6,
      "weight": 1343,
      "cylinder": 6,
      "torgue": 294,
      "img": "1954_Mercedes-Benz_300SL_Gullwing_Coupe.jpg"
    },
    {
      "id": 141,
      "year": 1998,
      "brand": "Mercedes-Benz",
      "model": "AMG CLK GTR",
      "topspeed": 323,
      "power": 464,
      "acceleration": 3.4,
      "weight": 1440,
      "cylinder": 12,
      "torgue": 731,
      "img": "1998_Mercedes-Benz_AMG_CLK_GTR.jpg"
    },
    {
      "id": 142,
      "year": 2005,
      "brand": "Mercedes-Benz",
      "model": "SLR",
      "topspeed": 334,
      "power": 460,
      "acceleration": 3.8,
      "weight": 1751,
      "cylinder": 8,
      "torgue": 780,
      "img": "2005_Mercedes-Benz_SLR.jpg"
    },
    {
      "id": 143,
      "year": 2009,
      "brand": "Mercedes-Benz",
      "model": "ML 63 AMG",
      "topspeed": 275,
      "power": 380,
      "acceleration": 5.1,
      "weight": 2286,
      "cylinder": 8,
      "torgue": 630,
      "img": "2009_Mercedes-Benz_ML_63_AMG.jpg"
    },
    {
      "id": 144,
      "year": 2009,
      "brand": "Mercedes-Benz",
      "model": "SL 65 AMG Black Series",
      "topspeed": 320,
      "power": 493,
      "acceleration": 3.8,
      "weight": 1912,
      "cylinder": 12,
      "torgue": 1001,
      "img": "2009_Mercedes-Benz_SL_65_AMG_Black_Series.jpg"
    },
    {
      "id": 145,
      "year": 2011,
      "brand": "Mercedes-Benz",
      "model": "SLS AMG",
      "topspeed": 323,
      "power": 426,
      "acceleration": 3.9,
      "weight": 1620,
      "cylinder": 8,
      "torgue": 650,
      "img": "2011_Mercedes-Benz_SLS_AMG.jpg"
    },
    {
      "id": 146,
      "year": 2012,
      "brand": "Mercedes-Benz",
      "model": "C63 AMG Black Series",
      "topspeed": 300,
      "power": 380,
      "acceleration": 3.9,
      "weight": 1748,
      "cylinder": 8,
      "torgue": 620,
      "img": "2012_Mercedes-Benz_C63_AMG_Black_Series.jpg"
    },
    {
      "id": 147,
      "year": 2012,
      "brand": "Mercedes-Benz",
      "model": "G65 AMG",
      "topspeed": 230,
      "power": 450,
      "acceleration": 5.2,
      "weight": 2580,
      "cylinder": 12,
      "torgue": 1000,
      "img": "2012_Mercedes-Benz_G65_AMG.jpg"
    },
    {
      "id": 148,
      "year": 2012,
      "brand": "Mercedes-Benz",
      "model": "S 65 AMG",
      "topspeed": 250,
      "power": 463,
      "acceleration": 4.4,
      "weight": 2275,
      "cylinder": 12,
      "torgue": 999,
      "img": "2012_Mercedes-Benz_S_65_AMG.jpg"
    },
    {
      "id": 149,
      "year": 1965,
      "brand": "MINI",
      "model": "Cooper S",
      "topspeed": 159,
      "power": 56,
      "acceleration": 10.4,
      "weight": 671,
      "cylinder": 4,
      "torgue": 108,
      "img": "1965_MINI_Cooper_S.jpg"
    },
    {
      "id": 150,
      "year": 2011,
      "brand": "MINI",
      "model": "Cooper S",
      "topspeed": 240,
      "power": 135,
      "acceleration": 6.4,
      "weight": 1215,
      "cylinder": 4,
      "torgue": 240,
      "img": "2011_MINI_Cooper_S.jpg"
    },
    {
      "id": 151,
      "year": 1999,
      "brand": "Mitsubishi",
      "model": "Lancer Evolution VI GSR",
      "topspeed": 250,
      "power": 209,
      "acceleration": 5.0,
      "weight": 1280,
      "cylinder": 4,
      "torgue": 407,
      "img": "1999_Mitsubishi_Lancer_Evolution_VI_GSR.jpg"
    },
    {
      "id": 152,
      "year": 2004,
      "brand": "Mitsubishi",
      "model": "Lancer Evolution VIII MR",
      "topspeed": 255,
      "power": 207,
      "acceleration": 5.2,
      "weight": 1410,
      "cylinder": 4,
      "torgue": 400,
      "img": "2004_Mitsubishi_Lancer_Evolution_VIII_MR.jpg"
    },
    {
      "id": 153,
      "year": 2008,
      "brand": "Mitsubishi",
      "model": "Lancer Evolution X GSR",
      "topspeed": 250,
      "power": 227,
      "acceleration": 5.7,
      "weight": 1540,
      "cylinder": 4,
      "torgue": 426,
      "img": "2008_Mitsubishi_Lancer_Evolution_X_GSR.jpg"
    },
    {
      "id": 154,
      "year": 1969,
      "brand": "Nissan",
      "model": "Fairlady Z 432",
      "topspeed": 199,
      "power": 119,
      "acceleration": 8.0,
      "weight": 1047,
      "cylinder": 6,
      "torgue": 180,
      "img": "1969_Nissan_Fairlady_Z_432.jpg"
    },
    {
      "id": 155,
      "year": 1970,
      "brand": "Nissan",
      "model": "Datsun 510",
      "topspeed": 160,
      "power": 72,
      "acceleration": 12.5,
      "weight": 965,
      "cylinder": 4,
      "torgue": 136,
      "img": "1970_Nissan_Datsun_510.jpg"
    },
    {
      "id": 156,
      "year": 1971,
      "brand": "Nissan",
      "model": "Skyline 2000GT-R",
      "topspeed": 193,
      "power": 119,
      "acceleration": 8.3,
      "weight": 1100,
      "cylinder": 6,
      "torgue": 180,
      "img": "1971_Nissan_Skyline_2000GT-R.jpg"
    },
    {
      "id": 157,
      "year": 1994,
      "brand": "Nissan",
      "model": "240SX SE",
      "topspeed": 221,
      "power": 116,
      "acceleration": 8.6,
      "weight": 1322,
      "cylinder": 4,
      "torgue": 217,
      "img": "1994_Nissan_240SX_SE.jpg"
    },
    {
      "id": 158,
      "year": 1998,
      "brand": "Nissan",
      "model": "R390",
      "topspeed": 355,
      "power": 410,
      "acceleration": 3.3,
      "weight": 1027,
      "cylinder": 8,
      "torgue": 639,
      "img": "1998_Nissan_R390.jpg"
    },
    {
      "id": 159,
      "year": 2000,
      "brand": "Nissan",
      "model": "Silvia spec-R",
      "topspeed": 266,
      "power": 186,
      "acceleration": 5.6,
      "weight": 1240,
      "cylinder": 4,
      "torgue": 275,
      "img": "2000_Nissan_Silvia_spec-R.jpg"
    },
    {
      "id": 160,
      "year": 2002,
      "brand": "Nissan",
      "model": "Skyline GTR V-spec",
      "topspeed": 251,
      "power": 244,
      "acceleration": 5.2,
      "weight": 1550,
      "cylinder": 6,
      "torgue": 397,
      "img": "2002_Nissan_GTR_V-spec.jpg"
    },
    {
      "id": 161,
      "year": 2010,
      "brand": "Nissan",
      "model": "370Z",
      "topspeed": 253,
      "power": 248,
      "acceleration": 5.4,
      "weight": 1482,
      "cylinder": 6,
      "torgue": 366,
      "img": "2010_Nissan_370Z.jpg"
    },
    {
      "id": 162,
      "year": 2012,
      "brand": "Nissan",
      "model": "GT-R Black Edition",
      "topspeed": 324,
      "power": 404,
      "acceleration": 3.1,
      "weight": 1763,
      "cylinder": 6,
      "torgue": 632,
      "img": "2012_Nissan_GT-R_Black_Edition.jpg"
    },
    {
      "id": 163,
      "year": 2010,
      "brand": "Noble",
      "model": "M600",
      "topspeed": 363,
      "power": 485,
      "acceleration": 3.2,
      "weight": 1250,
      "cylinder": 8,
      "torgue": 820,
      "img": "2010_Noble_M600.jpg"
    },
    {
      "id": 164,
      "year": 2009,
      "brand": "Pagani",
      "model": "Zonda Cinque Roadster",
      "topspeed": 349,
      "power": 506,
      "acceleration": 3.0,
      "weight": 1296,
      "cylinder": 12,
      "torgue": 780,
      "img": "2009_Pagani_Zonda_Cinque_Roadster.jpg"
    },
    {
      "id": 165,
      "year": 2010,
      "brand": "Pagani",
      "model": "Zonda R",
      "topspeed": 350,
      "power": 551,
      "acceleration": 2.7,
      "weight": 1150,
      "cylinder": 12,
      "torgue": 710,
      "img": "2010_Pagani_Zonda_R.jpg"
    },
    {
      "id": 166,
      "year": 2012,
      "brand": "Pagani",
      "model": "Huayra",
      "topspeed": 360,
      "power": 522,
      "acceleration": 3.3,
      "weight": 1430,
      "cylinder": 12,
      "torgue": 1000,
      "img": "2012_Pagani_Huayra.jpg"
    },
    {
      "id": 167,
      "year": 1984,
      "brand": "Peugeot",
      "model": "205 Turbo 16",
      "topspeed": 211,
      "power": 149,
      "acceleration": 6.0,
      "weight": 1145,
      "cylinder": 4,
      "torgue": 255,
      "img": "1984_Peugeot_205_Turbo_16.jpg"
    },
    {
      "id": 168,
      "year": 2004,
      "brand": "Peugeot",
      "model": "206 RC",
      "topspeed": 225,
      "power": 130,
      "acceleration": 7.4,
      "weight": 1100,
      "cylinder": 4,
      "torgue": 202,
      "img": "2004_Peugeot_206_RC.jpg"
    },
    {
      "id": 169,
      "year": 1969,
      "brand": "Pontiac",
      "model": "GTO Judge",
      "topspeed": 195,
      "power": 272,
      "acceleration": 5.4,
      "weight": 1643,
      "cylinder": 8,
      "torgue": 603,
      "img": "1969_Pontiac_GTO_Judge.jpg"
    },
    {
      "id": 170,
      "year": 1977,
      "brand": "Pontiac",
      "model": "Firebird Trans Am",
      "topspeed": 190,
      "power": 150,
      "acceleration": 8.1,
      "weight": 1724,
      "cylinder": 8,
      "torgue": 441,
      "img": "1977_Pontiac_Firebird_Trans_Am.jpg"
    },
    {
      "id": 171,
      "year": 2011,
      "brand": "Radical",
      "model": "SR8 RX",
      "topspeed": 286,
      "power": 343,
      "acceleration": 2.8,
      "weight": 650,
      "cylinder": 8,
      "torgue": 353,
      "img": "2011_Radical_SR8_RX.jpg"
    },
    {
      "id": 172,
      "year": 1987,
      "brand": "RUF",
      "model": "CTR Yellowbird",
      "topspeed": 342,
      "power": 350,
      "acceleration": 4.5,
      "weight": 1207,
      "cylinder": 6,
      "torgue": 556,
      "img": "1987_RUF_CTR_Yellowbird.jpg"
    },
    {
      "id": 173,
      "year": 1995,
      "brand": "RUF",
      "model": "CTR2",
      "topspeed": 347,
      "power": 388,
      "acceleration": 3.6,
      "weight": 1381,
      "cylinder": 6,
      "torgue": 685,
      "img": "1995_RUF_CTR2.jpg"
    },
    {
      "id": 174,
      "year": 2011,
      "brand": "RUF",
      "model": "RGT-8",
      "topspeed": 318,
      "power": 404,
      "acceleration": 3.7,
      "weight": 1350,
      "cylinder": 8,
      "torgue": 499,
      "img": "2011_RUF_RGT-8.jpg"
    },
    {
      "id": 175,
      "year": 2011,
      "brand": "RUF",
      "model": "Rt 12 R",
      "topspeed": 370,
      "power": 537,
      "acceleration": 3.1,
      "weight": 1476,
      "cylinder": 6,
      "torgue": 940,
      "img": "2011_RUF_Rt_12_R.jpg"
    },
    {
      "id": 176,
      "year": 2004,
      "brand": "Saleen",
      "model": "S7",
      "topspeed": 399,
      "power": 429,
      "acceleration": 4.2,
      "weight": 1250,
      "cylinder": 8,
      "torgue": 773,
      "img": "2004_Saleen_S7.jpg"
    },
    {
      "id": 177,
      "year": 2013,
      "brand": "Scion",
      "model": "FR-S",
      "topspeed": 209,
      "power": 149,
      "acceleration": 8.2,
      "weight": 1241,
      "cylinder": 4,
      "torgue": 205,
      "img": "2013_Scion_FR-S.jpg"
    },
    {
      "id": 178,
      "year": 1965,
      "brand": "Shelby",
      "model": "Cobra 427 SC",
      "topspeed": 300,
      "power": 317,
      "acceleration": 3.8,
      "weight": 1066,
      "cylinder": 8,
      "torgue": 678,
      "img": "1965_Shelby_Cobra_427_SC.jpg"
    },
    {
      "id": 179,
      "year": 1965,
      "brand": "Shelby",
      "model": "Cobra Daytona Coupe",
      "topspeed": 316,
      "power": 291,
      "acceleration": 4.4,
      "weight": 1043,
      "cylinder": 8,
      "torgue": 462,
      "img": "1965_Shelby_Cobra_Daytona_Coupe.jpg"
    },
    {
      "id": 180,
      "year": 2012,
      "brand": "Shelby",
      "model": "1000",
      "topspeed": 350,
      "power": 686,
      "acceleration": 4.0,
      "weight": 1723,
      "cylinder": 8,
      "torgue": 1017,
      "img": "2012_Shelby_1000.jpg"
    },
    {
      "id": 181,
      "year": 2010,
      "brand": "SSC",
      "model": "Ultimate Aero",
      "topspeed": 430,
      "power": 960,
      "acceleration": 3.1,
      "weight": 1247,
      "cylinder": 8,
      "torgue": 1508,
      "img": "2010_SSC_Ultimate_Aero.jpg"
    },
    {
      "id": 182,
      "year": 1998,
      "brand": "Subaru",
      "model": "Impreza 22B STi",
      "topspeed": 252,
      "power": 206,
      "acceleration": 4.6,
      "weight": 1270,
      "cylinder": 4,
      "torgue": 360,
      "img": "1998_Subaru_Impreza_22B_STi.jpg"
    },
    {
      "id": 183,
      "year": 2005,
      "brand": "Subaru",
      "model": "Impreza WRX STi",
      "topspeed": 255,
      "power": 232,
      "acceleration": 5.5,
      "weight": 1504,
      "cylinder": 4,
      "torgue": 422,
      "img": "2005_Subaru_Impreza_WRX_STi.jpg"
    },
    {
      "id": 184,
      "year": 2011,
      "brand": "Subaru",
      "model": "WRX STi",
      "topspeed": 250,
      "power": 227,
      "acceleration": 5.1,
      "weight": 1535,
      "cylinder": 4,
      "torgue": 393,
      "img": "2011_Subaru_WRX_STi.jpg"
    },
    {
      "id": 185,
      "year": 2013,
      "brand": "Subaru",
      "model": "BRZ",
      "topspeed": 226,
      "power": 149,
      "acceleration": 7.5,
      "weight": 1254,
      "cylinder": 4,
      "torgue": 205,
      "img": "2013_Subaru_BRZ.jpg"
    },
    {
      "id": 186,
      "year": 1985,
      "brand": "Toyota",
      "model": "Sprinter Trueno GT Apex",
      "topspeed": 195,
      "power": 95,
      "acceleration": 9.0,
      "weight": 950,
      "cylinder": 4,
      "torgue": 149,
      "img": "1985_Toyota_Sprinter_Trueno_GT_Apex.jpg"
    },
    {
      "id": 187,
      "year": 1992,
      "brand": "Toyota",
      "model": "Celica GT-Four RC ST185",
      "topspeed": 225,
      "power": 173,
      "acceleration": 7.7,
      "weight": 1460,
      "cylinder": 4,
      "torgue": 304,
      "img": "1992_Toyota_Celica_GT-Four_RC_ST185.jpg"
    },
    {
      "id": 188,
      "year": 1998,
      "brand": "Toyota",
      "model": "Supra RZ",
      "topspeed": 250,
      "power": 239,
      "acceleration": 5.3,
      "weight": 1510,
      "cylinder": 6,
      "torgue": 427,
      "img": "1998_Toyota_Supra_RC.jpg"
    },
    {
      "id": 189,
      "year": 2012,
      "brand": "Toyota",
      "model": "FJ Cruiser",
      "topspeed": 180,
      "power": 194,
      "acceleration": 7.7,
      "weight": 1965,
      "cylinder": 6,
      "torgue": 367,
      "img": "2012_Toyota_FJ_Cruiser.jpg"
    },
    {
      "id": 190,
      "year": 2005,
      "brand": "TVR",
      "model": "Sagaris",
      "topspeed": 295,
      "power": 303,
      "acceleration": 3.9,
      "weight": 1078,
      "cylinder": 6,
      "torgue": 473,
      "img": "2005_TVR_Sagaris.jpg"
    },
    {
      "id": 191,
      "year": 2012,
      "brand": "Ultima",
      "model": "GTR",
      "topspeed": 374,
      "power": 421,
      "acceleration": 2.7,
      "weight": 990,
      "cylinder": 8,
      "torgue": 727,
      "img": "2012_Ultima_GTR.jpg"
    },
    {
      "id": 192,
      "year": 2010,
      "brand": "Viper",
      "model": "SRT10 ACR-X",
      "topspeed": 328,
      "power": 477,
      "acceleration": 3.6,
      "weight": 1447,
      "cylinder": 10,
      "torgue": 820,
      "img": "2010_Viper_SRT10_ACR-X.jpg"
    },
    {
      "id": 193,
      "year": 2013,
      "brand": "Viper",
      "model": "GTS",
      "topspeed": 332,
      "power": 477,
      "acceleration": 3.4,
      "weight": 1495,
      "cylinder": 10,
      "torgue": 813,
      "img": "2013_Viper_GTS.jpg"
    },
    {
      "id": 194,
      "year": 1967,
      "brand": "Volkswagen",
      "model": "Beetle",
      "topspeed": 122,
      "power": 30,
      "acceleration": 28.0,
      "weight": 798,
      "cylinder": 4,
      "torgue": 88,
      "img": "1967_Volkswagen_Beetle.jpg"
    },
    {
      "id": 195,
      "year": 1984,
      "brand": "Volkswagen",
      "model": "Rabbit GTI",
      "topspeed": 178,
      "power": 67,
      "acceleration": 10.8,
      "weight": 953,
      "cylinder": 4,
      "torgue": 142,
      "img": "1984_Volkswagen_Rabbit_GTI.jpg"
    },
    {
      "id": 196,
      "year": 1992,
      "brand": "Volkswagen",
      "model": "Golf GTI 16v Mk2",
      "topspeed": 215,
      "power": 104,
      "acceleration": 8.3,
      "weight": 1100,
      "cylinder": 4,
      "torgue": 163,
      "img": "1992_Volkswagen_Golf_GTI_16v_Mk2.jpg"
    },
    {
      "id": 197,
      "year": 1995,
      "brand": "Volkswagen",
      "model": "Corrado VR6",
      "topspeed": 235,
      "power": 133,
      "acceleration": 6.9,
      "weight": 1240,
      "cylinder": 6,
      "torgue": 240,
      "img": "1995_Volkswagen_Corrado_VR6.jpg"
    },
    {
      "id": 198,
      "year": 2010,
      "brand": "Volkswagen",
      "model": "Golf R",
      "topspeed": 250,
      "power": 199,
      "acceleration": 5.2,
      "weight": 1446,
      "cylinder": 4,
      "torgue": 345,
      "img": "2010_Volkswagen_Golf_R.jpg"
    },
    {
      "id": 199,
      "year": 2011,
      "brand": "Volkswagen",
      "model": "Scirocco R",
      "topspeed": 250,
      "power": 195,
      "acceleration": 6.0,
      "weight": 1344,
      "cylinder": 4,
      "torgue": 350,
      "img": "2011_Volkswagen_Scirocco_R.jpg"
    }
  ]
}
